timeseries_exam/__init__.py
timeseries_exam/arch.py
timeseries_exam/content.py
timeseries_exam/model.py
timeseries_exam/number.py
timeseries_exam/syntax.py
timeseries_exam/syntax2.py
timeseries_exam-0.0.1.dist-info/LICENSE
timeseries_exam-0.0.1.dist-info/METADATA
timeseries_exam-0.0.1.dist-info/WHEEL
timeseries_exam-0.0.1.dist-info/top_level.txt
timeseries_exam-0.0.1.dist-info/RECORD
